tdfs/__init__.py
tdfs/featurestore.py
tdfs-0.0.4.dist-info/METADATA
tdfs-0.0.4.dist-info/WHEEL
tdfs-0.0.4.dist-info/top_level.txt
tdfs-0.0.4.dist-info/RECORD
