Metadata-Version: 2.1
Name: tdfs
Version: 0.0.4
Summary: Feature Store client using Teradata Dataframes
Home-page: UNKNOWN
Author: Teradata
Author-email: teradata.corporation@teradatacorporation.com
License: UNKNOWN
Platform: UNKNOWN
Requires-Python: >=3.6.0
Requires-Dist: teradataml (>=16.20.0.3)
